Metadata-Version: 1.1
Name: metzoo-python-opc-plugin
Version: 0.0.1
Summary: Python OPC Pluigin for Metzoo
Home-page: https://bitbucket.org/edrans/metzoo-python-opc-plugin
Author: Edrans
Author-email: info@edrans.com
License: MIT
Keywords: metzoo monitoring metric opc
Platform: UNKNOWN
Classifier: Development Status :: 4 - Beta
Classifier: License :: OSI Approved :: MIT License
Classifier: Programming Language :: Python :: 2.7
